Metadata-Version: 1.0
Name: giti
Version: 0.0.6
Summary: Command line tool for improve git
Home-page: http://github.com/xuzhuoyi/giti
Author: Zhuoyi Xu
Author-email: xzy476386434@vip.qq.com
License:                     GNU GENERAL PUBLIC LICENSE
